{"assembly":{".code":[{"begin":965,"end":3722,"name":"PUSH","value":"60"},{"begin":965,"end":3722,"name":"PUSH","value":"40"},{"begin":965,"end":3722,"name":"MSTORE"},{"begin":1664,"end":2261,"name":"CALLVALUE"},{"begin":1664,"end":2261,"name":"ISZERO"},{"begin":1664,"end":2261,"name":"PUSH [tag]","value":"1"},{"begin":1664,"end":2261,"name":"JUMPI"},{"begin":1664,"end":2261,"name":"PUSH","value":"0"},{"begin":1664,"end":2261,"name":"DUP1"},{"begin":1664,"end":2261,"name":"REVERT"},{"begin":1664,"end":2261,"name":"tag","value":"1"},{"begin":1664,"end":2261,"name":"JUMPDEST"},{"begin":1664,"end":2261,"name":"PUSH","value":"40"},{"begin":1664,"end":2261,"name":"MLOAD"},{"begin":1664,"end":2261,"name":"PUSHSIZE"},{"begin":1664,"end":2261,"name":"CODESIZE"},{"begin":1664,"end":2261,"name":"SUB"},{"begin":1664,"end":2261,"name":"DUP1"},{"begin":1664,"end":2261,"name":"PUSHSIZE"},{"begin":1664,"end":2261,"name":"DUP4"},{"begin":1664,"end":2261,"name":"CODECOPY"},{"begin":1664,"end":2261,"name":"DUP2"},{"begin":1664,"end":2261,"name":"ADD"},{"begin":1664,"end":2261,"name":"PUSH","value":"40"},{"begin":1664,"end":2261,"name":"MSTORE"},{"begin":1664,"end":2261,"name":"DUP1"},{"begin":1664,"end":2261,"name":"DUP1"},{"begin":1664,"end":2261,"name":"MLOAD"},{"begin":1664,"end":2261,"name":"DUP3"},{"begin":1664,"end":2261,"name":"ADD"},{"begin":1664,"end":2261,"name":"SWAP2"},{"begin":1664,"end":2261,"name":"SWAP1"},{"begin":1664,"end":2261,"name":"PUSH","value":"20"},{"begin":1664,"end":2261,"name":"ADD"},{"begin":1664,"end":2261,"name":"DUP1"},{"begin":1664,"end":2261,"name":"MLOAD"},{"begin":1664,"end":2261,"name":"SWAP2"},{"begin":1664,"end":2261,"name":"SWAP1"},{"begin":1664,"end":2261,"name":"PUSH","value":"20"},{"begin":1664,"end":2261,"name":"ADD"},{"begin":1664,"end":2261,"name":"DUP1"},{"begin":1664,"end":2261,"name":"MLOAD"},{"begin":1664,"end":2261,"name":"SWAP2"},{"begin":1664,"end":2261,"name":"SWAP1"},{"begin":1664,"end":2261,"name":"PUSH","value":"20"},{"begin":1664,"end":2261,"name":"ADD"},{"begin":1664,"end":2261,"name":"DUP1"},{"begin":1664,"end":2261,"name":"MLOAD"},{"begin":1664,"end":2261,"name":"SWAP2"},{"begin":1664,"end":2261,"name":"SWAP1"},{"begin":1664,"end":2261,"name":"PUSH","value":"20"},{"begin":1664,"end":2261,"name":"ADD"},{"begin":1664,"end":2261,"name":"DUP1"},{"begin":1664,"end":2261,"name":"MLOAD"},{"begin":1664,"end":2261,"name":"SWAP2"},{"begin":1664,"end":2261,"name":"SWAP1"},{"begin":1664,"end":2261,"name":"PUSH","value":"20"},{"begin":1664,"end":2261,"name":"ADD"},{"begin":1664,"end":2261,"name":"DUP1"},{"begin":1664,"end":2261,"name":"MLOAD"},{"begin":1664,"end":2261,"name":"SWAP2"},{"begin":1664,"end":2261,"name":"SWAP1"},{"begin":1664,"end":2261,"name":"PUSH","value":"20"},{"begin":1664,"end":2261,"name":"ADD"},{"begin":1664,"end":2261,"name":"DUP1"},{"begin":1664,"end":2261,"name":"MLOAD"},{"begin":1664,"end":2261,"name":"SWAP2"},{"begin":-1,"end":-1,"name":"POP"},{"begin":1948,"end":1960,"name":"PUSH","value":"0"},{"begin":1948,"end":1960,"name":"SWAP1"},{"begin":-1,"end":-1,"name":"POP"},{"begin":1963,"end":1976,"name":"DUP8"},{"begin":1963,"end":1976,"name":"DUP1"},{"begin":1948,"end":1976,"name":"MLOAD"},{"begin":1948,"end":1976,"name":"PUSH [tag]","value":"4"},{"begin":1948,"end":1976,"name":"SWAP3"},{"begin":1948,"end":1976,"name":"SWAP2"},{"begin":1948,"end":1976,"name":"PUSH","value":"20"},{"begin":1948,"end":1976,"name":"ADD"},{"begin":1948,"end":1976,"name":"SWAP1"},{"begin":1948,"end":1976,"name":"PUSH [tag]","value":"5"},{"begin":1948,"end":1976,"name":"JUMP","value":"[in]"},{"begin":1948,"end":1976,"name":"tag","value":"4"},{"begin":1948,"end":1976,"name":"JUMPDEST"},{"begin":-1,"end":-1,"name":"POP"},{"begin":1986,"end":2005,"name":"PUSH","value":"1"},{"begin":1986,"end":2028,"name":"SWAP6"},{"begin":1986,"end":2028,"name":"SWAP1"},{"begin":1986,"end":2028,"name":"SWAP6"},{"begin":1986,"end":2028,"name":"SSTORE"},{"begin":2038,"end":2057,"name":"PUSH","value":"2"},{"begin":2038,"end":2080,"name":"SWAP4"},{"begin":2038,"end":2080,"name":"SWAP1"},{"begin":2038,"end":2080,"name":"SWAP4"},{"begin":2038,"end":2080,"name":"SSTORE"},{"begin":2090,"end":2101,"name":"PUSH","value":"3"},{"begin":2090,"end":2116,"name":"SWAP2"},{"begin":2090,"end":2116,"name":"SWAP1"},{"begin":2090,"end":2116,"name":"SWAP2"},{"begin":2090,"end":2116,"name":"SSTORE"},{"begin":2126,"end":2142,"name":"PUSH","value":"4"},{"begin":2126,"end":2162,"name":"SSTORE"},{"begin":2172,"end":2197,"name":"PUSH","value":"5"},{"begin":2172,"end":2226,"name":"SSTORE"},{"begin":2236,"end":2243,"name":"PUSH","value":"6"},{"begin":2236,"end":2254,"name":"DUP1"},{"begin":2236,"end":2254,"name":"SLOAD"},{"begin":-1,"end":-1,"name":"PUSH","value":"1"},{"begin":-1,"end":-1,"name":"PUSH","value":"A0"},{"begin":-1,"end":-1,"name":"PUSH","value":"2"},{"begin":-1,"end":-1,"name":"EXP"},{"begin":-1,"end":-1,"name":"SUB"},{"begin":-1,"end":-1,"name":"NOT"},{"begin":2236,"end":2254,"name":"AND"},{"begin":-1,"end":-1,"name":"PUSH","value":"1"},{"begin":-1,"end":-1,"name":"PUSH","value":"A0"},{"begin":-1,"end":-1,"name":"PUSH","value":"2"},{"begin":-1,"end":-1,"name":"EXP"},{"begin":-1,"end":-1,"name":"SUB"},{"begin":2236,"end":2254,"name":"SWAP1"},{"begin":2236,"end":2254,"name":"SWAP3"},{"begin":2236,"end":2254,"name":"AND"},{"begin":2236,"end":2254,"name":"SWAP2"},{"begin":2236,"end":2254,"name":"SWAP1"},{"begin":2236,"end":2254,"name":"SWAP2"},{"begin":2236,"end":2254,"name":"OR"},{"begin":2236,"end":2254,"name":"SWAP1"},{"begin":2236,"end":2254,"name":"SSTORE"},{"begin":-1,"end":-1,"name":"POP"},{"begin":965,"end":3722,"name":"PUSH [tag]","value":"6"},{"begin":965,"end":3722,"name":"JUMP"},{"begin":965,"end":3722,"name":"tag","value":"5"},{"begin":965,"end":3722,"name":"JUMPDEST"},{"begin":965,"end":3722,"name":"DUP3"},{"begin":965,"end":3722,"name":"DUP1"},{"begin":965,"end":3722,"name":"SLOAD"},{"begin":965,"end":3722,"name":"PUSH","value":"1"},{"begin":965,"end":3722,"name":"DUP2"},{"begin":965,"end":3722,"name":"PUSH","value":"1"},{"begin":965,"end":3722,"name":"AND"},{"begin":965,"end":3722,"name":"ISZERO"},{"begin":965,"end":3722,"name":"PUSH","value":"100"},{"begin":965,"end":3722,"name":"MUL"},{"begin":965,"end":3722,"name":"SUB"},{"begin":965,"end":3722,"name":"AND"},{"begin":965,"end":3722,"name":"PUSH","value":"2"},{"begin":965,"end":3722,"name":"SWAP1"},{"begin":965,"end":3722,"name":"DIV"},{"begin":965,"end":3722,"name":"SWAP1"},{"begin":965,"end":3722,"name":"PUSH","value":"0"},{"begin":965,"end":3722,"name":"MSTORE"},{"begin":965,"end":3722,"name":"PUSH","value":"20"},{"begin":965,"end":3722,"name":"PUSH","value":"0"},{"begin":965,"end":3722,"name":"KECCAK256"},{"begin":965,"end":3722,"name":"SWAP1"},{"begin":965,"end":3722,"name":"PUSH","value":"1F"},{"begin":965,"end":3722,"name":"ADD"},{"begin":965,"end":3722,"name":"PUSH","value":"20"},{"begin":965,"end":3722,"name":"SWAP1"},{"begin":965,"end":3722,"name":"DIV"},{"begin":965,"end":3722,"name":"DUP2"},{"begin":965,"end":3722,"name":"ADD"},{"begin":965,"end":3722,"name":"SWAP3"},{"begin":965,"end":3722,"name":"DUP3"},{"begin":965,"end":3722,"name":"PUSH","value":"1F"},{"begin":965,"end":3722,"name":"LT"},{"begin":965,"end":3722,"name":"PUSH [tag]","value":"8"},{"begin":965,"end":3722,"name":"JUMPI"},{"begin":965,"end":3722,"name":"DUP1"},{"begin":965,"end":3722,"name":"MLOAD"},{"begin":965,"end":3722,"name":"PUSH","value":"FF"},{"begin":965,"end":3722,"name":"NOT"},{"begin":965,"end":3722,"name":"AND"},{"begin":965,"end":3722,"name":"DUP4"},{"begin":965,"end":3722,"name":"DUP1"},{"begin":965,"end":3722,"name":"ADD"},{"begin":965,"end":3722,"name":"OR"},{"begin":965,"end":3722,"name":"DUP6"},{"begin":965,"end":3722,"name":"SSTORE"},{"begin":965,"end":3722,"name":"PUSH [tag]","value":"10"},{"begin":965,"end":3722,"name":"JUMP"},{"begin":965,"end":3722,"name":"tag","value":"8"},{"begin":965,"end":3722,"name":"JUMPDEST"},{"begin":965,"end":3722,"name":"DUP3"},{"begin":965,"end":3722,"name":"DUP1"},{"begin":965,"end":3722,"name":"ADD"},{"begin":965,"end":3722,"name":"PUSH","value":"1"},{"begin":965,"end":3722,"name":"ADD"},{"begin":965,"end":3722,"name":"DUP6"},{"begin":965,"end":3722,"name":"SSTORE"},{"begin":965,"end":3722,"name":"DUP3"},{"begin":965,"end":3722,"name":"ISZERO"},{"begin":965,"end":3722,"name":"PUSH [tag]","value":"10"},{"begin":965,"end":3722,"name":"JUMPI"},{"begin":965,"end":3722,"name":"SWAP2"},{"begin":965,"end":3722,"name":"DUP3"},{"begin":965,"end":3722,"name":"ADD"},{"begin":965,"end":3722,"name":"tag","value":"9"},{"begin":965,"end":3722,"name":"JUMPDEST"},{"begin":965,"end":3722,"name":"DUP3"},{"begin":965,"end":3722,"name":"DUP2"},{"begin":965,"end":3722,"name":"GT"},{"begin":965,"end":3722,"name":"ISZERO"},{"begin":965,"end":3722,"name":"PUSH [tag]","value":"10"},{"begin":965,"end":3722,"name":"JUMPI"},{"begin":965,"end":3722,"name":"DUP3"},{"begin":965,"end":3722,"name":"MLOAD"},{"begin":965,"end":3722,"name":"DUP3"},{"begin":965,"end":3722,"name":"SSTORE"},{"begin":965,"end":3722,"name":"SWAP2"},{"begin":965,"end":3722,"name":"PUSH","value":"20"},{"begin":965,"end":3722,"name":"ADD"},{"begin":965,"end":3722,"name":"SWAP2"},{"begin":965,"end":3722,"name":"SWAP1"},{"begin":965,"end":3722,"name":"PUSH","value":"1"},{"begin":965,"end":3722,"name":"ADD"},{"begin":965,"end":3722,"name":"SWAP1"},{"begin":965,"end":3722,"name":"PUSH [tag]","value":"9"},{"begin":965,"end":3722,"name":"JUMP"},{"begin":965,"end":3722,"name":"tag","value":"10"},{"begin":965,"end":3722,"name":"JUMPDEST"},{"begin":-1,"end":-1,"name":"POP"},{"begin":965,"end":3722,"name":"PUSH [tag]","value":"11"},{"begin":965,"end":3722,"name":"SWAP3"},{"begin":965,"end":3722,"name":"SWAP2"},{"begin":-1,"end":-1,"name":"POP"},{"begin":965,"end":3722,"name":"PUSH [tag]","value":"12"},{"begin":965,"end":3722,"name":"JUMP","value":"[in]"},{"begin":965,"end":3722,"name":"tag","value":"11"},{"begin":965,"end":3722,"name":"JUMPDEST"},{"begin":965,"end":3722,"name":"POP"},{"begin":965,"end":3722,"name":"SWAP1"},{"begin":965,"end":3722,"name":"JUMP","value":"[out]"},{"begin":965,"end":3722,"name":"tag","value":"12"},{"begin":965,"end":3722,"name":"JUMPDEST"},{"begin":965,"end":3722,"name":"PUSH [tag]","value":"13"},{"begin":965,"end":3722,"name":"SWAP2"},{"begin":965,"end":3722,"name":"SWAP1"},{"begin":965,"end":3722,"name":"tag","value":"14"},{"begin":965,"end":3722,"name":"JUMPDEST"},{"begin":965,"end":3722,"name":"DUP1"},{"begin":965,"end":3722,"name":"DUP3"},{"begin":965,"end":3722,"name":"GT"},{"begin":965,"end":3722,"name":"ISZERO"},{"begin":965,"end":3722,"name":"PUSH [tag]","value":"11"},{"begin":965,"end":3722,"name":"JUMPI"},{"begin":965,"end":3722,"name":"PUSH","value":"0"},{"begin":965,"end":3722,"name":"DUP2"},{"begin":965,"end":3722,"name":"SSTORE"},{"begin":965,"end":3722,"name":"PUSH","value":"1"},{"begin":965,"end":3722,"name":"ADD"},{"begin":965,"end":3722,"name":"PUSH [tag]","value":"14"},{"begin":965,"end":3722,"name":"JUMP"},{"begin":965,"end":3722,"name":"tag","value":"13"},{"begin":965,"end":3722,"name":"JUMPDEST"},{"begin":965,"end":3722,"name":"SWAP1"},{"begin":965,"end":3722,"name":"JUMP","value":"[out]"},{"begin":965,"end":3722,"name":"tag","value":"6"},{"begin":965,"end":3722,"name":"JUMPDEST"},{"begin":965,"end":3722,"name":"PUSH #[$]","value":"0000000000000000000000000000000000000000000000000000000000000000"},{"begin":965,"end":3722,"name":"DUP1"},{"begin":965,"end":3722,"name":"PUSH [$]","value":"0000000000000000000000000000000000000000000000000000000000000000"},{"begin":965,"end":3722,"name":"PUSH","value":"0"},{"begin":965,"end":3722,"name":"CODECOPY"},{"begin":965,"end":3722,"name":"PUSH","value":"0"},{"begin":965,"end":3722,"name":"RETURN"}],".data":{"0":{".auxdata":"a165627a7a72305820e993d860b8894e9dc6109ca553049759833de6a434ef9818591ad7974ef0dc4f0029",".code":[{"begin":965,"end":3722,"name":"PUSH","value":"60"},{"begin":965,"end":3722,"name":"PUSH","value":"40"},{"begin":965,"end":3722,"name":"MSTORE"},{"begin":965,"end":3722,"name":"PUSH","value":"0"},{"begin":965,"end":3722,"name":"DUP1"},{"begin":965,"end":3722,"name":"REVERT"}]}}},"bytecode":"6060604052341561000f57600080fd5b6040516101843803806101848339810160405280805182019190602001805191906020018051919060200180519190602001805191906020018051919060200180519150600090508780516100689291602001906100a6565b5060019590955560029390935560039190915560045560055560068054600160a060020a031916600160a060020a0390921691909117905550610141565b828054600181600116156101000203166002900490600052602060002090601f016020900481019282601f106100e757805160ff1916838001178555610114565b82800160010185558215610114579182015b828111156101145782518255916020019190600101906100f9565b50610120929150610124565b5090565b61013e91905b80821115610120576000815560010161012a565b90565b60358061014f6000396000f3006060604052600080fd00a165627a7a72305820e993d860b8894e9dc6109ca553049759833de6a434ef9818591ad7974ef0dc4f0029","functionHashes":{},"gasEstimates":{"creation":[null,10600],"external":{},"internal":{}},"interface":"[{\"inputs\":[{\"name\":\"_contractName\",\"type\":\"string\"},{\"name\":\"_initialContribution\",\"type\":\"uint256\"},{\"name\":\"_monthlyContribution\",\"type\":\"uint256\"},{\"name\":\"_refundValue\",\"type\":\"uint256\"},{\"name\":\"_nMaxParticipants\",\"type\":\"uint256\"},{\"name\":\"_minVotePercentageToRefund\",\"type\":\"uint256\"},{\"name\":\"_creator\",\"type\":\"address\"}],\"payable\":false,\"stateMutability\":\"nonpayable\",\"type\":\"constructor\"}]","metadata":"{\"compiler\":{\"version\":\"0.4.19+commit.c4cbbb05\"},\"language\":\"Solidity\",\"output\":{\"abi\":[{\"inputs\":[{\"name\":\"_contractName\",\"type\":\"string\"},{\"name\":\"_initialContribution\",\"type\":\"uint256\"},{\"name\":\"_monthlyContribution\",\"type\":\"uint256\"},{\"name\":\"_refundValue\",\"type\":\"uint256\"},{\"name\":\"_nMaxParticipants\",\"type\":\"uint256\"},{\"name\":\"_minVotePercentageToRefund\",\"type\":\"uint256\"},{\"name\":\"_creator\",\"type\":\"address\"}],\"payable\":false,\"stateMutability\":\"nonpayable\",\"type\":\"constructor\"}],\"devdoc\":{\"methods\":{}},\"userdoc\":{\"methods\":{}}},\"settings\":{\"compilationTarget\":{\"\":\"SmartCarInsuranceContract\"},\"libraries\":{},\"optimizer\":{\"enabled\":true,\"runs\":200},\"remappings\":[]},\"sources\":{\"\":{\"keccak256\":\"0xa355cf4c53221c391d138b7a15fdc70ba9aee26f8cfb449eb94c67b76262a1dd\",\"urls\":[\"bzzr://203bf2d4e40da43df8506a7b9178f614cbb6dce26fcb7297bc30121ae212fce1\"]}},\"version\":1}","opcodes":"PUSH1 0x60 PUSH1 0x40 MSTORE CALLVALUE ISZERO PUSH2 0xF JUMPI PUSH1 0x0 DUP1 REVERT JUMPDEST PUSH1 0x40 MLOAD PUSH2 0x184 CODESIZE SUB DUP1 PUSH2 0x184 DUP4 CODECOPY DUP2 ADD PUSH1 0x40 MSTORE DUP1 DUP1 MLOAD DUP3 ADD SWAP2 SWAP1 PUSH1 0x20 ADD DUP1 MLOAD SWAP2 SWAP1 PUSH1 0x20 ADD DUP1 MLOAD SWAP2 SWAP1 PUSH1 0x20 ADD DUP1 MLOAD SWAP2 SWAP1 PUSH1 0x20 ADD DUP1 MLOAD SWAP2 SWAP1 PUSH1 0x20 ADD DUP1 MLOAD SWAP2 SWAP1 PUSH1 0x20 ADD DUP1 MLOAD SWAP2 POP PUSH1 0x0 SWAP1 POP DUP8 DUP1 MLOAD PUSH2 0x68 SWAP3 SWAP2 PUSH1 0x20 ADD SWAP1 PUSH2 0xA6 JUMP JUMPDEST POP PUSH1 0x1 SWAP6 SWAP1 SWAP6 SSTORE PUSH1 0x2 SWAP4 SWAP1 SWAP4 SSTORE PUSH1 0x3 SWAP2 SWAP1 SWAP2 SSTORE PUSH1 0x4 SSTORE PUSH1 0x5 SSTORE PUSH1 0x6 DUP1 SLOAD PUSH1 0x1 PUSH1 0xA0 PUSH1 0x2 EXP SUB NOT AND PUSH1 0x1 PUSH1 0xA0 PUSH1 0x2 EXP SUB SWAP1 SWAP3 AND SWAP2 SWAP1 SWAP2 OR SWAP1 SSTORE POP PUSH2 0x141 JUMP JUMPDEST DUP3 DUP1 SLOAD PUSH1 0x1 DUP2 PUSH1 0x1 AND ISZERO PUSH2 0x100 MUL SUB AND PUSH1 0x2 SWAP1 DIV SWAP1 PUSH1 0x0 MSTORE PUSH1 0x20 PUSH1 0x0 KECCAK256 SWAP1 PUSH1 0x1F ADD PUSH1 0x20 SWAP1 DIV DUP2 ADD SWAP3 DUP3 PUSH1 0x1F LT PUSH2 0xE7 JUMPI DUP1 MLOAD PUSH1 0xFF NOT AND DUP4 DUP1 ADD OR DUP6 SSTORE PUSH2 0x114 JUMP JUMPDEST DUP3 DUP1 ADD PUSH1 0x1 ADD DUP6 SSTORE DUP3 ISZERO PUSH2 0x114 JUMPI SWAP2 DUP3 ADD JUMPDEST DUP3 DUP2 GT ISZERO PUSH2 0x114 JUMPI DUP3 MLOAD DUP3 SSTORE SWAP2 PUSH1 0x20 ADD SWAP2 SWAP1 PUSH1 0x1 ADD SWAP1 PUSH2 0xF9 JUMP JUMPDEST POP PUSH2 0x120 SWAP3 SWAP2 POP PUSH2 0x124 JUMP JUMPDEST POP SWAP1 JUMP JUMPDEST PUSH2 0x13E SWAP2 SWAP1 JUMPDEST DUP1 DUP3 GT ISZERO PUSH2 0x120 JUMPI PUSH1 0x0 DUP2 SSTORE PUSH1 0x1 ADD PUSH2 0x12A JUMP JUMPDEST SWAP1 JUMP JUMPDEST PUSH1 0x35 DUP1 PUSH2 0x14F PUSH1 0x0 CODECOPY PUSH1 0x0 RETURN STOP PUSH1 0x60 PUSH1 0x40 MSTORE PUSH1 0x0 DUP1 REVERT STOP LOG1 PUSH6 0x627A7A723058 KECCAK256 0xe9 SWAP4 0xd8 PUSH1 0xB8 DUP10 0x4e SWAP14 0xc6 LT SWAP13 0xa5 MSTORE8 DIV SWAP8 MSIZE DUP4 RETURNDATASIZE 0xe6 LOG4 CALLVALUE 0xef SWAP9 XOR MSIZE BYTE 0xd7 SWAP8 0x4e CREATE 0xdc 0x4f STOP 0x29 ","runtimeBytecode":"6060604052600080fd00a165627a7a72305820e993d860b8894e9dc6109ca553049759833de6a434ef9818591ad7974ef0dc4f0029","srcmap":"965:2757:0:-;;;1664:597;;;;;;;;;;;;;;;;;;;;;;;;;;;;;;;;;;;;;;;;;;;;;;;;;;;;;;;;;;;;;;;-1:-1:-1;1948:12:0;;-1:-1:-1;1963:13:0;;1948:28;;;;;;;;:::i;:::-;-1:-1:-1;1986:19:0;:42;;;;2038:19;:42;;;;2090:11;:26;;;;2126:16;:36;2172:25;:54;2236:7;:18;;-1:-1:-1;;;;;;2236:18:0;-1:-1:-1;;;;;2236:18:0;;;;;;;;;-1:-1:-1;965:2757:0;;;;;;;;;;;;;;;;;;;;;;;;;;;;;;;;;;;;;;;;;;;;;;;;;;;;;;;;;;;;;;;;;;;;;;;;;;;;;;;;;;;;;;;;-1:-1:-1;965:2757:0;;;-1:-1:-1;965:2757:0;:::i;:::-;;;:::o;:::-;;;;;;;;;;;;;;;;;;;;:::o;:::-;;;;;;;","srcmapRuntime":"965:2757:0:-;;;;;"}
